{"assets/images/.DS_Store":["assets/images/.DS_Store"],"assets/images/LineTop.png":["assets/images/LineTop.png"],"assets/images/angry.png":["assets/images/angry.png"],"assets/images/anxiety.png":["assets/images/anxiety.png"],"assets/images/calendar.png":["assets/images/calendar.png"],"assets/images/close.png":["assets/images/close.png"],"assets/images/eye.png":["assets/images/eye.png"],"assets/images/flag.png":["assets/images/flag.png"],"assets/images/header_menu.png":["assets/images/header_menu.png"],"assets/images/heart.png":["assets/images/heart.png"],"assets/images/icAccepter.png":["assets/images/icAccepter.png"],"assets/images/icAddBlue.png":["assets/images/icAddBlue.png"],"assets/images/icBookOpen.png":["assets/images/icBookOpen.png"],"assets/images/icCalendar.png":["assets/images/icCalendar.png"],"assets/images/icCheck.png":["assets/images/icCheck.png"],"assets/images/icChevronRight.png":["assets/images/icChevronRight.png"],"assets/images/icChooseDate.png":["assets/images/icChooseDate.png"],"assets/images/icChooseFile.png":["assets/images/icChooseFile.png"],"assets/images/icChooseImage.png":["assets/images/icChooseImage.png"],"assets/images/icChooseVideo.png":["assets/images/icChooseVideo.png"],"assets/images/icClock.png":["assets/images/icClock.png"],"assets/images/icCloseModal.png":["assets/images/icCloseModal.png"],"assets/images/icDelete.png":["assets/images/icDelete.png"],"assets/images/icDeleteCircle.png":["assets/images/icDeleteCircle.png"],"assets/images/icDocument.png":["assets/images/icDocument.png"],"assets/images/icEditFilter.png":["assets/images/icEditFilter.png"],"assets/images/icFlag.png":["assets/images/icFlag.png"],"assets/images/icGiaoViec.png":["assets/images/icGiaoViec.png"],"assets/images/icHeart.png":["assets/images/icHeart.png"],"assets/images/icHome.png":["assets/images/icHome.png"],"assets/images/icList.png":["assets/images/icList.png"],"assets/images/icLoc.png":["assets/images/icLoc.png"],"assets/images/icMan.png":["assets/images/icMan.png"],"assets/images/icManyPeople.png":["assets/images/icManyPeople.png"],"assets/images/icModel.png":["assets/images/icModel.png"],"assets/images/icMoreVertical.png":["assets/images/icMoreVertical.png"],"assets/images/icNhacNho.png":["assets/images/icNhacNho.png"],"assets/images/icOClock.png":["assets/images/icOClock.png"],"assets/images/icPinBold.png":["assets/images/icPinBold.png"],"assets/images/icPiority.png":["assets/images/icPiority.png"],"assets/images/icProject.png":["assets/images/icProject.png"],"assets/images/icProjectS.png":["assets/images/icProjectS.png"],"assets/images/icSearch.png":["assets/images/icSearch.png"],"assets/images/icSend.png":["assets/images/icSend.png"],"assets/images/icSwitchOff.png":["assets/images/icSwitchOff.png"],"assets/images/icSwitchOn.png":["assets/images/icSwitchOn.png"],"assets/images/icTag.png":["assets/images/icTag.png"],"assets/images/icToDay.png":["assets/images/icToDay.png"],"assets/images/icTouchChuaChon.png":["assets/images/icTouchChuaChon.png"],"assets/images/icTouchDaChon.png":["assets/images/icTouchDaChon.png"],"assets/images/icUser.png":["assets/images/icUser.png"],"assets/images/icWorkingHour.png":["assets/images/icWorkingHour.png"],"assets/images/ic_arrow_down.png":["assets/images/ic_arrow_down.png"],"assets/images/ic_calendar.png":["assets/images/ic_calendar.png"],"assets/images/ic_loading.png":["assets/images/ic_loading.png"],"assets/images/ic_search.png":["assets/images/ic_search.png"],"assets/images/icon_arrow_left.png":["assets/images/icon_arrow_left.png"],"assets/images/icon_avt_assignTask.png":["assets/images/icon_avt_assignTask.png"],"assets/images/icon_list.png":["assets/images/icon_list.png"],"assets/images/icon_message.png":["assets/images/icon_message.png"],"assets/images/icon_pin.png":["assets/images/icon_pin.png"],"assets/images/icon_tick_circle.png":["assets/images/icon_tick_circle.png"],"assets/images/imgUserDefault.png":["assets/images/imgUserDefault.png"],"assets/images/jwAddTime.png":["assets/images/jwAddTime.png"],"assets/images/jwMucDo.png":["assets/images/jwMucDo.png"],"assets/images/jwTime.png":["assets/images/jwTime.png"],"assets/images/jwTinhTrang.png":["assets/images/jwTinhTrang.png"],"assets/images/logoUnitedKingdom.png":["assets/images/logoUnitedKingdom.png"],"assets/images/logoVietNam.png":["assets/images/logoVietNam.png"],"assets/images/manager.png":["assets/images/manager.png"],"assets/images/positive.png":["assets/images/positive.png"],"assets/images/seen.png":["assets/images/seen.png"],"assets/images/smile.png":["assets/images/smile.png"],"assets/images/surprised.png":["assets/images/surprised.png"],"assets/images/tag_task.png":["assets/images/tag_task.png"],"assets/images/thumb-up.png":["assets/images/thumb-up.png"],"assets/lang/en.json":["assets/lang/en.json"],"assets/lang/vi.json":["assets/lang/vi.json"],"assets/lottie/Empty.json":["assets/lottie/Empty.json"],"packages/cupertino_icons/assets/CupertinoIcons.ttf":["packages/cupertino_icons/assets/CupertinoIcons.ttf"],"packages/flex_color_picker/assets/opacity.png":["packages/flex_color_picker/assets/opacity.png"],"packages/fluttertoast/assets/toastify.css":["packages/fluttertoast/assets/toastify.css"],"packages/fluttertoast/assets/toastify.js":["packages/fluttertoast/assets/toastify.js"]}